mlflow_gcp_iap/__init__.py
mlflow_gcp_iap/cli.py
mlflow_gcp_iap/config.py
mlflow_gcp_iap/oidc.py
mlflow_gcp_iap/refresher.py
mlflow_gcp_iap/test.py
mlflow_gcp_iap-0.0.3.dist-info/licenses/LICENSE
mlflow_gcp_iap-0.0.3.dist-info/METADATA
mlflow_gcp_iap-0.0.3.dist-info/WHEEL
mlflow_gcp_iap-0.0.3.dist-info/entry_points.txt
mlflow_gcp_iap-0.0.3.dist-info/top_level.txt
mlflow_gcp_iap-0.0.3.dist-info/RECORD
