Metadata-Version: 2.4
Name: mlflow-gcp-iap
Version: 0.0.3
Summary: Add-on for accessing MlFlow tracking server behing GCP IAP.
Author: AiBox Lab
Maintainer-email: Moésio Filho <moesio.f@gmail.com>
Project-URL: Homepage, https://github.com/aiboxlab/mlflow-gcp-iap
Project-URL: Repository, https://github.com/aiboxlab/mlflow-gcp-iap
Project-URL: Issues, https://github.com/aiboxlab/mlflow-gcp-iap/issues
Classifier: Programming Language :: Python :: 3.10
Classifier: Programming Language :: Python :: 3.11
Classifier: Programming Language :: Python :: 3.12
Classifier: Programming Language :: Python :: 3.13
Classifier: Development Status :: 3 - Alpha
Requires-Python: >=3.10
License-File: LICENSE
Requires-Dist: google-auth>=2.38,~=2.40.0
Requires-Dist: platformdirs>=4.0.0
Requires-Dist: pydantic-settings>=2.0.0
Requires-Dist: requests>=2.32.5
Requires-Dist: typer>=0.17.4
Requires-Dist: uv>=0.8.15
Requires-Dist: mlflow>=2.19.0
Dynamic: license-file
